<?xml version="1.0" encoding="UTF-8" standalone="yes"?>
<?mso-application progid="Excel.Sheet"?>
<Workbook xmlns="urn:schemas-microsoft-com:office:spreadsheet" xmlns:o="urn:schemas-microsoft-com:office:office" xmlns:x="urn:schemas-microsoft-com:office:excel" xmlns:ss="urn:schemas-microsoft-com:office:spreadsheet" xmlns:html="http://www.w3.org/TR/REC-html40" xmlns:dt="uuid:C2F41010-65B3-11d1-A29F-00AA00C14882"><DocumentProperties xmlns="urn:schemas-microsoft-com:office:office"><Author>Administrator</Author><LastAuthor>山角岩</LastAuthor><Created>2014-06-11T14:47:06Z</Created><LastSaved>2018-10-11T07:49:37Z</LastSaved></DocumentProperties><CustomDocumentProperties xmlns="urn:schemas-microsoft-com:office:office"><KSOProductBuildVer dt:dt="string">2052-10.1.0.7469</KSOProductBuildVer></CustomDocumentProperties><ExcelWorkbook xmlns="urn:schemas-microsoft-com:office:excel"><WindowWidth>25095</WindowWidth><WindowHeight>12600</WindowHeight><ActiveSheet>1</ActiveSheet><ProtectStructure>False</ProtectStructure><ProtectWindows>False</ProtectWindows></ExcelWorkbook><Styles><Style ss:ID="s8" ss:Name="千位分隔"><NumberFormat ss:Format="_ * #,##0.00_ ;_ * \-#,##0.00_ ;_ * &quot;-&quot;??_ ;_ @_ "/></Style><Style ss:ID="s4" ss:Name="货币"><NumberFormat ss:Format="_ &quot;￥&quot;* #,##0.00_ ;_ &quot;￥&quot;* \-#,##0.00_ ;_ &quot;￥&quot;* &quot;-&quot;??_ ;_ @_ "/></Style><Style ss:ID="Default" ss:Name="Normal"><Alignment/><Borders/><Font ss:FontName="宋体" x:CharSet="134" ss:Size="11" ss:Color="#000000"/><Interior/><NumberFormat/><Protection/></Style><Style ss:ID="s49" ss:Name="40% - 强调文字颜色 6"><Font ss:FontName="宋体" x:CharSet="0" ss:Size="11" ss:Color="#000000"/><Interior ss:Color="#C6E0B4" ss:Pattern="Solid"/></Style><Style ss:ID="s43" ss:Name="40% - 强调文字颜色 4"><Font ss:FontName="宋体" x:CharSet="0" ss:Size="11" ss:Color="#000000"/><Interior ss:Color="#FFE699" ss:Pattern="Solid"/></Style><Style ss:ID="s39" ss:Name="40% - 强调文字颜色 2"><Font ss:FontName="宋体" x:CharSet="0" ss:Size="11" ss:Color="#000000"/><Interior ss:Color="#F8CBAD" ss:Pattern="Solid"/></Style><Style ss:ID="s15" ss:Name="标题 4"><Font ss:FontName="宋体" x:CharSet="134" ss:Size="11" ss:Color="#44546A" ss:Bold="1"/></Style><Style ss:ID="s12" ss:Name="已访问的超链接"><Font ss:FontName="宋体" x:CharSet="0" ss:Size="11" ss:Color="#800080" ss:Underline="Single"/></Style><Style ss:ID="s7" ss:Name="差"><Font ss:FontName="宋体" x:CharSet="0" ss:Size="11" ss:Color="#9C0006"/><Interior ss:Color="#FFC7CE" ss:Pattern="Solid"/></Style><Style ss:ID="s46" ss:Name="40% - 强调文字颜色 5"><Font ss:FontName="宋体" x:CharSet="0" ss:Size="11" ss:Color="#000000"/><Interior ss:Color="#B4C6E7" ss:Pattern="Solid"/></Style><Style ss:ID="s37" ss:Name="40% - 强调文字颜色 1"><Font ss:FontName="宋体" x:CharSet="0" ss:Size="11" ss:Color="#000000"/><Interior ss:Color="#BDD7EE" ss:Pattern="Solid"/></Style><Style ss:ID="s26" ss:Name="检查单元格"><Borders><Border ss:Position="Bottom" ss:LineStyle="Double" ss:Weight="3" ss:Color="#3F3F3F"/><Border ss:Position="Left" ss:LineStyle="Double" ss:Weight="3" ss:Color="#3F3F3F"/><Border ss:Position="Right" ss:LineStyle="Double" ss:Weight="3" ss:Color="#3F3F3F"/><Border ss:Position="Top" ss:LineStyle="Double" ss:Weight="3" ss:Color="#3F3F3F"/></Borders><Font ss:FontName="宋体" x:CharSet="0" ss:Size="11" ss:Color="#FFFFFF" ss:Bold="1"/><Interior ss:Color="#A5A5A5" ss:Pattern="Solid"/></Style><Style ss:ID="s18" ss:Name="解释性文本"><Font ss:FontName="宋体" x:CharSet="0" ss:Size="11" ss:Color="#7F7F7F" ss:Italic="1"/></Style><Style ss:ID="s6" ss:Name="40% - 强调文字颜色 3"><Font ss:FontName="宋体" x:CharSet="0" ss:Size="11" ss:Color="#000000"/><Interior ss:Color="#DBDBDB" ss:Pattern="Solid"/></Style><Style ss:ID="s47" ss:Name="60% - 强调文字颜色 5"><Font ss:FontName="宋体" x:CharSet="0" ss:Size="11" ss:Color="#FFFFFF"/><Interior ss:Color="#8EA9DB" ss:Pattern="Solid"/></Style><Style ss:ID="s30" ss:Name="链接单元格"><Borders><Border ss:Position="Bottom" ss:LineStyle="Double" ss:Weight="3" ss:Color="#FF8001"/></Borders><Font ss:FontName="宋体" x:CharSet="0" ss:Size="11" ss:Color="#FA7D00"/></Style><Style ss:ID="s21" ss:Name="60% - 强调文字颜色 1"><Font ss:FontName="宋体" x:CharSet="0" ss:Size="11" ss:Color="#FFFFFF"/><Interior ss:Color="#9BC2E6" ss:Pattern="Solid"/></Style><Style ss:ID="s19" ss:Name="标题 1"><Borders><Border ss:Position="Bottom" ss:LineStyle="Continuous" ss:Weight="2" ss:Color="#5B9BD5"/></Borders><Font ss:FontName="宋体" x:CharSet="134" ss:Size="15" ss:Color="#44546A" ss:Bold="1"/></Style><Style ss:ID="s9" ss:Name="60% - 强调文字颜色 3"><Font ss:FontName="宋体" x:CharSet="0" ss:Size="11" ss:Color="#FFFFFF"/><Interior ss:Color="#C9C9C9" ss:Pattern="Solid"/></Style><Style ss:ID="s5" ss:Name="千位分隔[0]"><NumberFormat ss:Format="_ * #,##0_ ;_ * \-#,##0_ ;_ * &quot;-&quot;_ ;_ @_ "/></Style><Style ss:ID="s50" ss:Name="60% - 强调文字颜色 6"><Font ss:FontName="宋体" x:CharSet="0" ss:Size="11" ss:Color="#FFFFFF"/><Interior ss:Color="#A9D08E" ss:Pattern="Solid"/></Style><Style ss:ID="s33" ss:Name="适中"><Font ss:FontName="宋体" x:CharSet="0" ss:Size="11" ss:Color="#9C6500"/><Interior ss:Color="#FFEB9C" ss:Pattern="Solid"/></Style><Style ss:ID="s23" ss:Name="60% - 强调文字颜色 4"><Font ss:FontName="宋体" x:CharSet="0" ss:Size="11" ss:Color="#FFFFFF"/><Interior ss:Color="#FFD966" ss:Pattern="Solid"/></Style><Style ss:ID="s14" ss:Name="60% - 强调文字颜色 2"><Font ss:FontName="宋体" x:CharSet="0" ss:Size="11" ss:Color="#FFFFFF"/><Interior ss:Color="#F4B084" ss:Pattern="Solid"/></Style><Style ss:ID="s13" ss:Name="注释"><Borders><Border ss:Position="Bottom" ss:LineStyle="Continuous" ss:Weight="1" ss:Color="#B2B2B2"/><Border ss:Position="Left" ss:LineStyle="Continuous" ss:Weight="1" ss:Color="#B2B2B2"/><Border ss:Position="Right" ss:LineStyle="Continuous" ss:Weight="1" ss:Color="#B2B2B2"/><Border ss:Position="Top" ss:LineStyle="Continuous" ss:Weight="1" ss:Color="#B2B2B2"/></Borders><Interior ss:Color="#FFFFCC" ss:Pattern="Solid"/></Style><Style ss:ID="s3" ss:Name="输入"><Borders><Border ss:Position="Bottom" ss:LineStyle="Continuous" ss:Weight="1" ss:Color="#7F7F7F"/><Border ss:Position="Left" ss:LineStyle="Continuous" ss:Weight="1" ss:Color="#7F7F7F"/><Border ss:Position="Right" ss:LineStyle="Continuous" ss:Weight="1" ss:Color="#7F7F7F"/><Border ss:Position="Top" ss:LineStyle="Continuous" ss:Weight="1" ss:Color="#7F7F7F"/></Borders><Font ss:FontName="宋体" x:CharSet="0" ss:Size="11" ss:Color="#3F3F76"/><Interior ss:Color="#FFCC99" ss:Pattern="Solid"/></Style><Style ss:ID="s45" ss:Name="常规 2 2"><Alignment/><Borders/><Font ss:FontName="宋体" x:CharSet="134" ss:Size="11" ss:Color="#000000"/><Interior/><NumberFormat/><Protection/></Style><Style ss:ID="s36" ss:Name="20% - 强调文字颜色 1"><Font ss:FontName="宋体" x:CharSet="0" ss:Size="11" ss:Color="#000000"/><Interior ss:Color="#DDEBF7" ss:Pattern="Solid"/></Style><Style ss:ID="s34" ss:Name="20% - 强调文字颜色 5"><Font ss:FontName="宋体" x:CharSet="0" ss:Size="11" ss:Color="#000000"/><Interior ss:Color="#D9E1F2" ss:Pattern="Solid"/></Style><Style ss:ID="s25" ss:Name="计算"><Borders><Border ss:Position="Bottom" ss:LineStyle="Continuous" ss:Weight="1" ss:Color="#7F7F7F"/><Border ss:Position="Left" ss:LineStyle="Continuous" ss:Weight="1" ss:Color="#7F7F7F"/><Border ss:Position="Right" ss:LineStyle="Continuous" ss:Weight="1" ss:Color="#7F7F7F"/><Border ss:Position="Top" ss:LineStyle="Continuous" ss:Weight="1" ss:Color="#7F7F7F"/></Borders><Font ss:FontName="宋体" x:CharSet="0" ss:Size="11" ss:Color="#FA7D00" ss:Bold="1"/><Interior ss:Color="#F2F2F2" ss:Pattern="Solid"/></Style><Style ss:ID="s17" ss:Name="标题"><Font ss:FontName="宋体" x:CharSet="134" ss:Size="18" ss:Color="#44546A" ss:Bold="1"/></Style><Style ss:ID="s2" ss:Name="20% - 强调文字颜色 3"><Font ss:FontName="宋体" x:CharSet="0" ss:Size="11" ss:Color="#000000"/><Interior ss:Color="#EDEDED" ss:Pattern="Solid"/></Style><Style ss:ID="s48" ss:Name="强调文字颜色 6"><Font ss:FontName="宋体" x:CharSet="0" ss:Size="11" ss:Color="#FFFFFF"/><Interior ss:Color="#70AD47" ss:Pattern="Solid"/></Style><Style ss:ID="s41" ss:Name="强调文字颜色 4"><Font ss:FontName="宋体" x:CharSet="0" ss:Size="11" ss:Color="#FFFFFF"/><Interior ss:Color="#FFC000" ss:Pattern="Solid"/></Style><Style ss:ID="s31" ss:Name="汇总"><Borders><Border ss:Position="Bottom" ss:LineStyle="Double" ss:Weight="3" ss:Color="#5B9BD5"/><Border ss:Position="Top" ss:LineStyle="Continuous" ss:Weight="1" ss:Color="#5B9BD5"/></Borders><Font ss:FontName="宋体" x:CharSet="0" ss:Size="11" ss:Color="#000000" ss:Bold="1"/></Style><Style ss:ID="s29" ss:Name="强调文字颜色 2"><Font ss:FontName="宋体" x:CharSet="0" ss:Size="11" ss:Color="#FFFFFF"/><Interior ss:Color="#ED7D31" ss:Pattern="Solid"/></Style><Style ss:ID="s20" ss:Name="标题 2"><Borders><Border ss:Position="Bottom" ss:LineStyle="Continuous" ss:Weight="2" ss:Color="#5B9BD5"/></Borders><Font ss:FontName="宋体" x:CharSet="134" ss:Size="13" ss:Color="#44546A" ss:Bold="1"/></Style><Style ss:ID="s1" ss:Name="货币[0]"><NumberFormat ss:Format="_ &quot;￥&quot;* #,##0_ ;_ &quot;￥&quot;* \-#,##0_ ;_ &quot;￥&quot;* &quot;-&quot;_ ;_ @_ "/></Style><Style ss:ID="s42" ss:Name="20% - 强调文字颜色 4"><Font ss:FontName="宋体" x:CharSet="0" ss:Size="11" ss:Color="#000000"/><Interior ss:Color="#FFF2CC" ss:Pattern="Solid"/></Style><Style ss:ID="s38" ss:Name="20% - 强调文字颜色 2"><Font ss:FontName="宋体" x:CharSet="0" ss:Size="11" ss:Color="#000000"/><Interior ss:Color="#FCE4D6" ss:Pattern="Solid"/></Style><Style ss:ID="s32" ss:Name="好"><Font ss:FontName="宋体" x:CharSet="0" ss:Size="11" ss:Color="#006100"/><Interior ss:Color="#C6EFCE" ss:Pattern="Solid"/></Style><Style ss:ID="s28" ss:Name="20% - 强调文字颜色 6"><Font ss:FontName="宋体" x:CharSet="0" ss:Size="11" ss:Color="#000000"/><Interior ss:Color="#E2EFDA" ss:Pattern="Solid"/></Style><Style ss:ID="s22" ss:Name="标题 3"><Borders><Border ss:Position="Bottom" ss:LineStyle="Continuous" ss:Weight="2" ss:Color="#ACCCEA"/></Borders><Font ss:FontName="宋体" x:CharSet="134" ss:Size="11" ss:Color="#44546A" ss:Bold="1"/></Style><Style ss:ID="s10" ss:Name="超链接"><Font ss:FontName="宋体" x:CharSet="0" ss:Size="11" ss:Color="#0000FF" ss:Underline="Single"/></Style><Style ss:ID="s11" ss:Name="百分比"><NumberFormat ss:Format="0%"/></Style><Style ss:ID="s44" ss:Name="强调文字颜色 5"><Font ss:FontName="宋体" x:CharSet="0" ss:Size="11" ss:Color="#FFFFFF"/><Interior ss:Color="#4472C4" ss:Pattern="Solid"/></Style><Style ss:ID="s40" ss:Name="强调文字颜色 3"><Font ss:FontName="宋体" x:CharSet="0" ss:Size="11" ss:Color="#FFFFFF"/><Interior ss:Color="#A5A5A5" ss:Pattern="Solid"/></Style><Style ss:ID="s35" ss:Name="强调文字颜色 1"><Font ss:FontName="宋体" x:CharSet="0" ss:Size="11" ss:Color="#FFFFFF"/><Interior ss:Color="#5B9BD5" ss:Pattern="Solid"/></Style><Style ss:ID="s27" ss:Name="好 2"><Font ss:FontName="宋体" x:CharSet="134" ss:Size="11" ss:Color="#008000"/><Interior ss:Color="#CCFFCC" ss:Pattern="Solid"/></Style><Style ss:ID="s24" ss:Name="输出"><Borders><Border ss:Position="Bottom" ss:LineStyle="Continuous" ss:Weight="1" ss:Color="#3F3F3F"/><Border ss:Position="Left" ss:LineStyle="Continuous" ss:Weight="1" ss:Color="#3F3F3F"/><Border ss:Position="Right" ss:LineStyle="Continuous" ss:Weight="1" ss:Color="#3F3F3F"/><Border ss:Position="Top" ss:LineStyle="Continuous" ss:Weight="1" ss:Color="#3F3F3F"/></Borders><Font ss:FontName="宋体" x:CharSet="0" ss:Size="11" ss:Color="#3F3F3F" ss:Bold="1"/><Interior ss:Color="#F2F2F2" ss:Pattern="Solid"/></Style><Style ss:ID="s16" ss:Name="警告文本"><Font ss:FontName="宋体" x:CharSet="0" ss:Size="11" ss:Color="#FF0000"/></Style><Style ss:ID="s51"><Alignment/><Borders/><Font ss:FontName="宋体" x:CharSet="134" ss:Size="11" ss:Color="#000000"/><Interior/><NumberFormat/><Protection/></Style><Style ss:ID="s52"><Alignment ss:Horizontal="Center"/><Borders/><Font ss:FontName="微软雅黑" x:CharSet="134" x:Family="Swiss" ss:Size="10" ss:Color="#000000"/><Interior/><NumberFormat/><Protection/></Style><Style ss:ID="s53"><Alignment ss:Horizontal="Center"/><Font ss:FontName="微软雅黑" x:CharSet="134" x:Family="Swiss" ss:Size="10" ss:Color="#000000"/></Style><Style ss:ID="s54"><Alignment ss:Horizontal="Center"/><Font ss:FontName="微软雅黑" x:CharSet="134" x:Family="Swiss" ss:Size="10"/><Interior/></Style><Style ss:ID="s55"><Alignment ss:Horizontal="Center"/><Borders/><Font ss:FontName="微软雅黑" x:CharSet="134" x:Family="Swiss" ss:Size="10"/><Interior/><NumberFormat/><Protection/></Style><Style ss:ID="s56" ss:Parent="s27"><Alignment ss:Horizontal="Center"/><Font ss:FontName="微软雅黑" x:CharSet="134" x:Family="Swiss" ss:Size="10" ss:Bold="1"/><Interior/></Style><Style ss:ID="s57" ss:Parent="s45"><Alignment ss:Horizontal="Center"/><Borders/><Font ss:FontName="微软雅黑" x:CharSet="134" x:Family="Swiss" ss:Size="10" ss:Color="#333300"/><Interior/></Style><Style ss:ID="s58"><Alignment ss:Horizontal="Center"/></Style><Style ss:ID="s59"><Alignment ss:Horizontal="Center"/><Font ss:FontName="宋体" x:CharSet="134" ss:Size="11" ss:Color="#000000"/></Style><Style ss:ID="s60"><Alignment ss:Horizontal="Center"/><Borders/><Font ss:FontName="宋体" x:CharSet="134" ss:Size="11" ss:Color="#000000"/><Interior/><NumberFormat/><Protection/></Style></Styles><Worksheet ss:Name="配置"><Table ss:ExpandedColumnCount="8" ss:ExpandedRowCount="2" x:FullColumns="1" x:FullRows="1" ss:DefaultColumnWidth="54" ss:DefaultRowHeight="13.5"><Column ss:Index="1" ss:StyleID="s51" ss:AutoFitWidth="0" ss:Width="186"/><Column ss:Index="2" ss:StyleID="s51" ss:AutoFitWidth="0" ss:Width="121.5"/><Column ss:StyleID="s51" ss:AutoFitWidth="0" ss:Width="254.25"/><Column ss:StyleID="s51" ss:AutoFitWidth="0" ss:Width="66"/><Column ss:StyleID="s51" ss:AutoFitWidth="0" ss:Width="57.75"/><Column ss:StyleID="s51" ss:AutoFitWidth="0" ss:Width="176.25"/><Column ss:StyleID="s51" ss:AutoFitWidth="0" ss:Width="125.25"/><Column ss:StyleID="s51" ss:AutoFitWidth="0" ss:Width="240"/><Row ss:StyleID="s58"><Cell ss:StyleID="s58"><Data ss:Type="String">服务端文件名</Data></Cell><Cell ss:StyleID="s58"><Data ss:Type="String">服务端对应工作表号</Data></Cell><Cell ss:StyleID="s58"><Data ss:Type="String">客户端文件名</Data></Cell><Cell ss:StyleID="s58"><Data ss:Type="String">客户端对应工作表号</Data></Cell><Cell ss:StyleID="s58"><Data ss:Type="String">erl头部</Data></Cell><Cell ss:StyleID="s58"><Data ss:Type="String">erl内容格式</Data></Cell><Cell ss:StyleID="s58"><Data ss:Type="String">erl尾部</Data></Cell><Cell ss:StyleID="s58"><Data ss:Type="String">客户端特殊处理</Data></Cell></Row><Row ss:Height="86.05"><Cell ss:StyleID="s59"><Data ss:Type="String">config_reward_center.txt</Data></Cell><Cell ss:StyleID="s60"><Data ss:Type="Number">1</Data></Cell><Cell ss:StyleID="s58"><Data ss:Type="String">config_reward_center.cnf|RewardCenter</Data></Cell><Cell ss:StyleID="s60"><Data ss:Type="Number">1</Data></Cell><Cell ss:Index="6"><Data ss:Type="String">get(stage) -&gt; #$</Data></Cell><Cell ss:Index="8" ss:StyleID="s60"><Data ss:Type="String">2=&gt;type</Data></Cell></Row></Table><WorksheetOptions xmlns="urn:schemas-microsoft-com:office:excel"><PageSetup><Header x:Margin="0.3"/><Footer x:Margin="0.3"/><PageMargins x:Left="0.7" x:Right="0.7" x:Top="0.75" x:Bottom="0.75"/></PageSetup><TopRowVisible>0</TopRowVisible><LeftColumnVisible>0</LeftColumnVisible><Panes><Pane><Number>3</Number><ActiveRow>6</ActiveRow><ActiveCol>7</ActiveCol><RangeSelection>R7C8</RangeSelection></Pane></Panes><ProtectObjects>False</ProtectObjects><ProtectScenarios>False</ProtectScenarios></WorksheetOptions></Worksheet><Worksheet ss:Name="奖励配置"><Table ss:ExpandedColumnCount="7" ss:ExpandedRowCount="45" x:FullColumns="1" x:FullRows="1" ss:StyleID="s52" ss:DefaultColumnWidth="54" ss:DefaultRowHeight="16.5"><Column ss:Index="1" ss:StyleID="s52" ss:AutoFitWidth="0" ss:Width="77.25"/><Column ss:Index="2" ss:StyleID="s52" ss:AutoFitWidth="0" ss:Width="131.25"/><Column ss:StyleID="s52" ss:AutoFitWidth="0" ss:Width="118.5"/><Column ss:StyleID="s52" ss:AutoFitWidth="0" ss:Width="189"/><Column ss:StyleID="s52" ss:AutoFitWidth="0" ss:Width="217.5"/><Column ss:StyleID="s52" ss:AutoFitWidth="0" ss:Width="290.25"/><Column ss:StyleID="s52" ss:AutoFitWidth="0" ss:Width="92.25"/><Row><Cell ss:StyleID="s53"><Data ss:Type="String">type|reward_id</Data></Cell><Cell ss:StyleID="s53"><Data ss:Type="String">reward_type|reward_type</Data></Cell><Cell ss:StyleID="s52"><Data ss:Type="String">title|</Data></Cell><Cell ss:StyleID="s54"><Data ss:Type="String">award_item_id_list|award_item_id_list</Data></Cell><Cell ss:StyleID="s54"><Data ss:Type="String">award_item_num_list|award_item_num_list</Data></Cell><Cell ss:StyleID="s53"><Data ss:Type="String">desc|</Data></Cell><Cell ss:StyleID="s53"><Data ss:Type="String">param_flag|</Data></Cell></Row><Row><Cell ss:StyleID="s53"><Data ss:Type="String">不可空</Data></Cell><Cell ss:StyleID="s53"><Data ss:Type="String">不可空</Data></Cell><Cell ss:StyleID="s53"><Data ss:Type="String">不可空</Data></Cell><Cell ss:StyleID="s52"><Data ss:Type="String">可空#不需字段</Data></Cell><Cell ss:StyleID="s52"><Data ss:Type="String">可空#不需字段</Data></Cell><Cell ss:StyleID="s53"><Data ss:Type="String">不可空</Data></Cell><Cell ss:StyleID="s53"><Data ss:Type="String">不可空</Data></Cell></Row><Row><Cell ss:StyleID="s53"><Data ss:Type="String">数字</Data></Cell><Cell ss:StyleID="s53"><Data ss:Type="String">数字</Data></Cell><Cell ss:StyleID="s53"><Data ss:Type="String">字符串</Data></Cell><Cell ss:StyleID="s52"><Data ss:Type="String">一维数组</Data></Cell><Cell ss:StyleID="s52"><Data ss:Type="String">一维数组</Data></Cell><Cell ss:StyleID="s53"><Data ss:Type="String">字符串</Data></Cell><Cell ss:StyleID="s53"><Data ss:Type="String">数字</Data></Cell></Row><Row><Cell ss:Index="4" ss:StyleID="s53"><Data ss:Type="String">不定长</Data></Cell><Cell ss:StyleID="s53"><Data ss:Type="String">不定长</Data></Cell></Row><Row><Cell ss:Index="4" ss:StyleID="s55"/><Cell ss:StyleID="s55"/></Row><Row><Cell ss:StyleID="s52"><Data ss:Type="String">奖励ID</Data></Cell><Cell ss:StyleID="s52"><Data ss:Type="String">奖励类型</Data><Comment ss:Author="Administrator"><ss:Data xmlns="http://www.w3.org/TR/REC-html40"><Font html:Color="#000000"></Font><Font html:Face="宋体" x:CharSet="134" html:Size="9">Administrator:&#10;1=竞技场排名奖励&#10;2=叛军击杀钻石奖励&#10;3=叛军分享击杀钻石奖励&#10;4=世界BOSS荣誉排名奖励&#10;5=世界BOSS伤害排名奖励&#10;6=GM发放奖励(奖励从控制台输入)&#10;7=叛军伤害排行奖励&#10;8=叛军功勋排行奖励&#10;9=助战奖励&#10;13=7天活动排行奖励&#10;14=充值钻石返利&#10;15=王者赛排名奖励&#10;16=王者赛段位奖励</Font></ss:Data></Comment></Cell><Cell ss:StyleID="s52"><Data ss:Type="String">奖励标题</Data></Cell><Cell ss:StyleID="s56"><Data ss:Type="String">奖励的物品Id列表</Data></Cell><Cell ss:StyleID="s56"><Data ss:Type="String">奖励的物品数量列表</Data></Cell><Cell ss:StyleID="s52"><Data ss:Type="String">奖励描述</Data></Cell><Cell ss:StyleID="s52"><Data ss:Type="String">参数标志</Data><Comment ss:Author="Administrator"><ss:Data xmlns="http://www.w3.org/TR/REC-html40"><Font html:Color="#000000"></Font><Font html:Face="宋体" x:CharSet="134" html:Size="9">Administrator:&#10;0 = 不需要参数&#10;1 = 一个数值参数&#10;2 = 一个字符串参数&#10;3 = 两个参数(字符串在前)&#10;4 = 两个参数(数值在前)</Font></ss:Data></Comment></Cell></Row><Row><Cell ss:StyleID="s52"><Data ss:Type="Number">1</Data></Cell><Cell ss:StyleID="s52"><Data ss:Type="Number">1</Data></Cell><Cell ss:StyleID="s57"><Data ss:Type="String">竞技场排名奖励</Data></Cell><Cell ss:StyleID="s57"/><Cell ss:StyleID="s57"/><Cell ss:StyleID="s52"><Data ss:Type="String">你在竞技场中获得了【%d名】，获得以上奖励</Data></Cell><Cell ss:StyleID="s52"><Data ss:Type="Number">1</Data></Cell></Row><Row><Cell ss:StyleID="s52"><Data ss:Type="Number">2</Data></Cell><Cell ss:StyleID="s52"><Data ss:Type="Number">2</Data></Cell><Cell ss:StyleID="s52"><Data ss:Type="String">击杀入侵者</Data></Cell><Cell ss:Index="6" ss:StyleID="s52"><Data ss:Type="String">入侵者【%s】被你无情的击杀，你获得了击杀奖励</Data></Cell><Cell ss:StyleID="s52"><Data ss:Type="Number">2</Data></Cell></Row><Row><Cell ss:StyleID="s52"><Data ss:Type="Number">3</Data></Cell><Cell ss:StyleID="s52"><Data ss:Type="Number">3</Data></Cell><Cell ss:StyleID="s52"><Data ss:Type="String">发现的入侵者被击杀</Data></Cell><Cell ss:Index="6" ss:StyleID="s52"><Data ss:Type="String">你发现了入侵者【%s】,获得以上奖励</Data></Cell><Cell ss:StyleID="s52"><Data ss:Type="Number">2</Data></Cell></Row><Row><Cell ss:StyleID="s52"><Data ss:Type="Number">4</Data></Cell><Cell ss:StyleID="s52"><Data ss:Type="Number">4</Data></Cell><Cell ss:StyleID="s52"><Data ss:Type="String">世界BOSS荣誉排名奖励</Data></Cell><Cell ss:Index="6" ss:StyleID="s52"><Data ss:Type="String">你在世界BOSS中荣誉排名第%d，获得奖励</Data></Cell><Cell ss:StyleID="s52"><Data ss:Type="Number">1</Data></Cell></Row><Row><Cell ss:StyleID="s52"><Data ss:Type="Number">5</Data></Cell><Cell ss:StyleID="s52"><Data ss:Type="Number">5</Data></Cell><Cell ss:StyleID="s52"><Data ss:Type="String">世界BOSS伤害排名奖励</Data></Cell><Cell ss:Index="6" ss:StyleID="s52"><Data ss:Type="String">你在世界BOSS中伤害排名第%d，获得奖励</Data></Cell><Cell ss:StyleID="s52"><Data ss:Type="Number">1</Data></Cell></Row><Row><Cell ss:StyleID="s52"><Data ss:Type="Number">6</Data></Cell><Cell ss:StyleID="s52"><Data ss:Type="Number">6</Data></Cell><Cell ss:StyleID="s52"><Data ss:Type="String">服务器维护补偿</Data></Cell><Cell ss:StyleID="s52"><Data ss:Type="String">10000|19103|19005</Data></Cell><Cell ss:StyleID="s52"><Data ss:Type="String">2|10|200</Data></Cell><Cell ss:StyleID="s52"><Data ss:Type="String">以下为本次服务器维护补偿</Data></Cell><Cell ss:StyleID="s52"><Data ss:Type="Number">0</Data></Cell></Row><Row><Cell ss:StyleID="s52"><Data ss:Type="Number">7</Data></Cell><Cell ss:StyleID="s52"><Data ss:Type="Number">7</Data></Cell><Cell ss:StyleID="s52"><Data ss:Type="String">异度入侵伤害排行奖励</Data></Cell><Cell ss:Index="6" ss:StyleID="s52"><Data ss:Type="String">你在异度入侵伤害排名第%d，获得以上奖励</Data></Cell><Cell ss:StyleID="s52"><Data ss:Type="Number">1</Data></Cell></Row><Row><Cell ss:StyleID="s52"><Data ss:Type="Number">8</Data></Cell><Cell ss:StyleID="s52"><Data ss:Type="Number">8</Data></Cell><Cell ss:StyleID="s52"><Data ss:Type="String">异度入侵功勋排行奖励</Data></Cell><Cell ss:Index="6" ss:StyleID="s52"><Data ss:Type="String">你在异度入侵功勋排名第%d，获得以上奖励</Data></Cell><Cell ss:StyleID="s52"><Data ss:Type="Number">1</Data></Cell></Row><Row><Cell ss:StyleID="s52"><Data ss:Type="Number">9</Data></Cell><Cell ss:StyleID="s52"><Data ss:Type="Number">6</Data></Cell><Cell ss:StyleID="s52"><Data ss:Type="String">GM补偿</Data></Cell><Cell ss:Index="6" ss:StyleID="s52"><Data ss:Type="String">以下为GM给您发放的补偿奖励</Data></Cell><Cell ss:StyleID="s52"><Data ss:Type="Number">0</Data></Cell></Row><Row><Cell ss:StyleID="s52"><Data ss:Type="Number">10</Data></Cell><Cell ss:StyleID="s52"><Data ss:Type="Number">6</Data></Cell><Cell ss:StyleID="s52"><Data ss:Type="String">VIP福利</Data></Cell><Cell ss:Index="6" ss:StyleID="s52"><Data ss:Type="String">请领取奖励~</Data></Cell><Cell ss:StyleID="s52"><Data ss:Type="Number">0</Data></Cell></Row><Row><Cell ss:StyleID="s52"><Data ss:Type="Number">11</Data></Cell><Cell ss:StyleID="s52"><Data ss:Type="Number">9</Data></Cell><Cell ss:StyleID="s52"><Data ss:Type="String">助战奖励</Data></Cell><Cell ss:Index="6" ss:StyleID="s52"><Data ss:Type="String">好友【%s】使用了您的英雄，获得了%d友情点</Data></Cell><Cell ss:StyleID="s52"><Data ss:Type="Number">3</Data></Cell></Row><Row><Cell ss:StyleID="s52"><Data ss:Type="Number">12</Data></Cell><Cell ss:StyleID="s52"><Data ss:Type="Number">10</Data></Cell><Cell ss:StyleID="s52"><Data ss:Type="String">跨服对决排行奖励</Data></Cell><Cell ss:Index="6" ss:StyleID="s52"><Data ss:Type="String">你在跨服对决排名第%d，获得以上奖励</Data></Cell><Cell ss:StyleID="s52"><Data ss:Type="Number">1</Data></Cell></Row><Row><Cell ss:StyleID="s52"><Data ss:Type="Number">13</Data></Cell><Cell ss:StyleID="s52"><Data ss:Type="Number">11</Data></Cell><Cell ss:StyleID="s52"><Data ss:Type="String">怪物攻城排行奖励</Data></Cell><Cell ss:Index="6" ss:StyleID="s52"><Data ss:Type="String">你在怪物攻城排名第%d，获得以上奖励</Data></Cell><Cell ss:StyleID="s52"><Data ss:Type="Number">1</Data></Cell></Row><Row><Cell ss:StyleID="s52"><Data ss:Type="Number">14</Data></Cell><Cell ss:StyleID="s52"><Data ss:Type="Number">12</Data></Cell><Cell ss:StyleID="s52"><Data ss:Type="String">无尽深渊排行奖励</Data></Cell><Cell ss:Index="6" ss:StyleID="s52"><Data ss:Type="String">你在无尽深渊排名第%d，获得以上奖励</Data></Cell><Cell ss:StyleID="s52"><Data ss:Type="Number">1</Data></Cell></Row><Row><Cell ss:StyleID="s52"><Data ss:Type="Number">15</Data></Cell><Cell ss:StyleID="s52"><Data ss:Type="Number">6</Data></Cell><Cell ss:StyleID="s52"><Data ss:Type="String">服务器维护补偿</Data></Cell><Cell ss:StyleID="s52"><Data ss:Type="Number">19005</Data></Cell><Cell ss:StyleID="s52"><Data ss:Type="Number">100</Data></Cell><Cell ss:StyleID="s52"><Data ss:Type="String">服务器临时维护补偿</Data></Cell><Cell ss:StyleID="s52"><Data ss:Type="Number">0</Data></Cell></Row><Row><Cell ss:StyleID="s52"><Data ss:Type="Number">16</Data></Cell><Cell ss:StyleID="s52"><Data ss:Type="Number">13</Data></Cell><Cell ss:StyleID="s52"><Data ss:Type="String">冲榜战力榜排行奖励</Data></Cell><Cell ss:Index="6" ss:StyleID="s52"><Data ss:Type="String">你在冲榜活动战力榜中获得了【%d名】，获得以上奖励</Data></Cell><Cell ss:StyleID="s52"><Data ss:Type="Number">1</Data></Cell></Row><Row><Cell ss:StyleID="s52"><Data ss:Type="Number">17</Data></Cell><Cell ss:StyleID="s52"><Data ss:Type="Number">13</Data></Cell><Cell ss:StyleID="s52"><Data ss:Type="String">冲榜副本榜排行奖励</Data></Cell><Cell ss:Index="6" ss:StyleID="s52"><Data ss:Type="String">你在冲榜活动主线副本榜中获得了【%d名】，获得以上奖励</Data></Cell><Cell ss:StyleID="s52"><Data ss:Type="Number">1</Data></Cell></Row><Row><Cell ss:StyleID="s52"><Data ss:Type="Number">18</Data></Cell><Cell ss:StyleID="s52"><Data ss:Type="Number">13</Data></Cell><Cell ss:StyleID="s52"><Data ss:Type="String">冲榜竞技榜排行奖励</Data></Cell><Cell ss:Index="6" ss:StyleID="s52"><Data ss:Type="String">你在冲榜活动竞技榜中获得了【%d名】，获得以上奖励</Data></Cell><Cell ss:StyleID="s52"><Data ss:Type="Number">1</Data></Cell></Row><Row><Cell ss:StyleID="s52"><Data ss:Type="Number">19</Data></Cell><Cell ss:StyleID="s52"><Data ss:Type="Number">14</Data></Cell><Cell ss:StyleID="s52"><Data ss:Type="String">封测充值钻石返利</Data></Cell><Cell ss:Index="6" ss:StyleID="s52"><Data ss:Type="String">封测充值双倍钻石返利已发送，谢谢您一如既往的支持</Data></Cell><Cell ss:StyleID="s52"><Data ss:Type="Number">0</Data></Cell></Row><Row><Cell ss:StyleID="s52"><Data ss:Type="Number">20</Data></Cell><Cell ss:StyleID="s52"><Data ss:Type="Number">6</Data></Cell><Cell ss:StyleID="s52"><Data ss:Type="String">发现bug奖励</Data></Cell><Cell ss:Index="6" ss:StyleID="s52"><Data ss:Type="String">感谢你提供的bug以及建议</Data></Cell><Cell ss:StyleID="s52"><Data ss:Type="Number">0</Data></Cell></Row><Row><Cell ss:StyleID="s52"><Data ss:Type="Number">21</Data></Cell><Cell ss:StyleID="s52"><Data ss:Type="Number">15</Data></Cell><Cell ss:StyleID="s52"><Data ss:Type="String">王者赛排名奖</Data></Cell><Cell ss:Index="6" ss:StyleID="s52"><Data ss:Type="String">你在王者赛中位于【王者组第%s名】，获得以上奖励</Data></Cell><Cell ss:StyleID="s52"><Data ss:Type="Number">1</Data></Cell></Row><Row><Cell ss:StyleID="s52"><Data ss:Type="Number">22</Data></Cell><Cell ss:StyleID="s52"><Data ss:Type="Number">16</Data></Cell><Cell ss:StyleID="s52"><Data ss:Type="String">王者赛段位奖</Data></Cell><Cell ss:Index="6" ss:StyleID="s52"><Data ss:Type="String">你在本赛季王者赛中最终位于【%s】，获得以上奖励</Data></Cell><Cell ss:StyleID="s52"><Data ss:Type="Number">1</Data></Cell></Row><Row><Cell ss:StyleID="s52"><Data ss:Type="Number">23</Data></Cell><Cell ss:StyleID="s52"><Data ss:Type="Number">6</Data></Cell><Cell ss:StyleID="s52"><Data ss:Type="String">维护时间延长补偿</Data></Cell><Cell ss:Index="6" ss:StyleID="s52"><Data ss:Type="String">本次维护更新由于部分原因时间延长，请谅解</Data></Cell><Cell ss:StyleID="s52"><Data ss:Type="Number">0</Data></Cell></Row><Row ss:StyleID="s52"><Cell ss:StyleID="s52"><Data ss:Type="Number">24</Data></Cell><Cell ss:StyleID="s52"><Data ss:Type="Number">6</Data></Cell><Cell ss:StyleID="s52"><Data ss:Type="String">游戏异常补偿</Data></Cell><Cell ss:Index="6" ss:StyleID="s52"><Data ss:Type="String">十分抱歉，最近时间游戏异常导致玩家体验不愉快，请领取补偿</Data></Cell><Cell ss:StyleID="s52"><Data ss:Type="Number">0</Data></Cell></Row><Row><Cell ss:StyleID="s52"><Data ss:Type="Number">25</Data></Cell><Cell ss:StyleID="s52"><Data ss:Type="Number">17</Data></Cell><Cell ss:StyleID="s52"><Data ss:Type="String">转盘积分排行奖励</Data></Cell><Cell ss:Index="6" ss:StyleID="s52"><Data ss:Type="String">你在转盘积分排行榜中获得了【%d名】，获得以上奖励</Data></Cell><Cell ss:StyleID="s52"><Data ss:Type="Number">1</Data></Cell></Row><Row ss:StyleID="s52"><Cell ss:StyleID="s52"><Data ss:Type="Number">26</Data></Cell><Cell ss:StyleID="s52"><Data ss:Type="Number">6</Data></Cell><Cell ss:StyleID="s52"><Data ss:Type="String">幸运奖励</Data></Cell><Cell ss:Index="6" ss:StyleID="s52"><Data ss:Type="String">恭喜你获得Facebook粉丝页活动幸运奖励</Data></Cell><Cell ss:StyleID="s52"><Data ss:Type="Number">0</Data></Cell></Row><Row ss:StyleID="s52"><Cell ss:StyleID="s52"><Data ss:Type="Number">27</Data></Cell><Cell ss:StyleID="s52"><Data ss:Type="Number">6</Data></Cell><Cell ss:StyleID="s52"><Data ss:Type="String">福利派送</Data></Cell><Cell ss:Index="6" ss:StyleID="s52"><Data ss:Type="String">请领取一下福利</Data></Cell><Cell ss:StyleID="s52"><Data ss:Type="Number">0</Data></Cell></Row><Row ss:StyleID="s52"><Cell ss:StyleID="s52"><Data ss:Type="Number">28</Data></Cell><Cell ss:StyleID="s52"><Data ss:Type="Number">18</Data></Cell><Cell ss:StyleID="s52"><Data ss:Type="String">积分赛奖励</Data></Cell><Cell ss:Index="6" ss:StyleID="s52"><Data ss:Type="String">你在本期积分赛中获得了【%d名】，获得以上奖励</Data></Cell><Cell ss:StyleID="s52"><Data ss:Type="Number">1</Data></Cell></Row><Row><Cell ss:StyleID="s52"><Data ss:Type="Number">29</Data></Cell><Cell ss:StyleID="s52"><Data ss:Type="Number">19</Data></Cell><Cell ss:StyleID="s52"><Data ss:Type="String">资源战积分奖励</Data></Cell><Cell ss:Index="6" ss:StyleID="s52"><Data ss:Type="String">你在占领的【%s】中获得积分奖励</Data></Cell><Cell ss:StyleID="s52"><Data ss:Type="Number">1</Data></Cell></Row><Row><Cell ss:StyleID="s52"><Data ss:Type="Number">30</Data></Cell><Cell ss:StyleID="s52"><Data ss:Type="Number">20</Data></Cell><Cell ss:StyleID="s52"><Data ss:Type="String">资源战特殊奖励</Data></Cell><Cell ss:Index="6" ss:StyleID="s52"><Data ss:Type="String">你在占领的【%s】中获得特殊奖励</Data></Cell><Cell ss:StyleID="s52"><Data ss:Type="Number">1</Data></Cell></Row><Row><Cell ss:StyleID="s52"><Data ss:Type="Number">31</Data></Cell><Cell ss:StyleID="s52"><Data ss:Type="Number">21</Data></Cell><Cell ss:StyleID="s52"><Data ss:Type="String">星球战奖励</Data></Cell><Cell ss:Index="6" ss:StyleID="s52"><Data ss:Type="String">你的军团在%d（星球名）的星球战中成功推倒防御塔，获得奖励</Data></Cell><Cell ss:StyleID="s52"><Data ss:Type="Number">1</Data></Cell></Row><Row><Cell ss:StyleID="s52"><Data ss:Type="Number">32</Data></Cell><Cell ss:StyleID="s52"><Data ss:Type="Number">22</Data></Cell><Cell ss:StyleID="s52"><Data ss:Type="String">星球战奖励</Data></Cell><Cell ss:Index="6" ss:StyleID="s52"><Data ss:Type="String">你的军团在%d（星球名）的星球战中进攻胜利，获得奖励</Data></Cell><Cell ss:StyleID="s52"><Data ss:Type="Number">1</Data></Cell></Row><Row><Cell ss:StyleID="s52"><Data ss:Type="Number">33</Data></Cell><Cell ss:StyleID="s52"><Data ss:Type="Number">23</Data></Cell><Cell ss:StyleID="s52"><Data ss:Type="String">星球战奖励</Data></Cell><Cell ss:Index="6" ss:StyleID="s52"><Data ss:Type="String">你的军团在%d（星球名）的星球战中进攻战败</Data></Cell><Cell ss:StyleID="s52"><Data ss:Type="Number">1</Data></Cell></Row><Row><Cell ss:StyleID="s52"><Data ss:Type="Number">34</Data></Cell><Cell ss:StyleID="s52"><Data ss:Type="Number">24</Data></Cell><Cell ss:StyleID="s52"><Data ss:Type="String">星球战奖励</Data></Cell><Cell ss:Index="6" ss:StyleID="s52"><Data ss:Type="String">你的军团在%d（星球名）的星球战中防守成功，获得奖励</Data></Cell><Cell ss:StyleID="s52"><Data ss:Type="Number">1</Data></Cell></Row><Row><Cell ss:StyleID="s52"><Data ss:Type="Number">35</Data></Cell><Cell ss:StyleID="s52"><Data ss:Type="Number">25</Data></Cell><Cell ss:StyleID="s52"><Data ss:Type="String">星球战奖励</Data></Cell><Cell ss:Index="6" ss:StyleID="s52"><Data ss:Type="String">你的军团在%d（星球名）的星球战中防守失败，并失去了占领权</Data></Cell><Cell ss:StyleID="s52"><Data ss:Type="Number">1</Data></Cell></Row><Row><Cell ss:StyleID="s52"><Data ss:Type="Number">36</Data></Cell><Cell ss:StyleID="s52"><Data ss:Type="Number">26</Data></Cell><Cell ss:StyleID="s52"><Data ss:Type="String">星球战排行奖励</Data></Cell><Cell ss:Index="6" ss:StyleID="s52"><Data ss:Type="String">你在本次星球战活动中获得积分排名第%d名，获得奖</Data></Cell><Cell ss:StyleID="s52"><Data ss:Type="Number">1</Data></Cell></Row><Row><Cell ss:StyleID="s52"><Data ss:Type="Number">100</Data></Cell><Cell ss:StyleID="s52"><Data ss:Type="Number">27</Data></Cell><Cell ss:StyleID="s52"><Data ss:Type="String">payment</Data></Cell><Cell ss:Index="6" ss:StyleID="s52"><Data ss:Type="String">您在本次充值获得以上奖励</Data></Cell><Cell ss:StyleID="s52"><Data ss:Type="Number">0</Data></Cell></Row><Row><Cell ss:StyleID="s52"><Data ss:Type="Number">101</Data></Cell><Cell ss:StyleID="s52"><Data ss:Type="Number">28</Data></Cell><Cell ss:StyleID="s52"><Data ss:Type="String">cashback</Data></Cell><Cell ss:Index="6" ss:StyleID="s52"><Data ss:Type="String">您在本次充值获得以上奖励</Data></Cell><Cell ss:StyleID="s52"><Data ss:Type="Number">0</Data></Cell></Row><Row><Cell ss:StyleID="s52"><Data ss:Type="Number">102</Data></Cell><Cell ss:StyleID="s52"><Data ss:Type="Number">29</Data></Cell><Cell ss:StyleID="s52"><Data ss:Type="String">bonus</Data></Cell><Cell ss:Index="6" ss:StyleID="s52"><Data ss:Type="String">您在本次充值获得以上奖励</Data></Cell><Cell ss:StyleID="s52"><Data ss:Type="Number">0</Data></Cell></Row></Table><WorksheetOptions xmlns="urn:schemas-microsoft-com:office:excel"><PageSetup><Header x:Margin="0.3"/><Footer x:Margin="0.3"/><PageMargins x:Left="0.7" x:Right="0.7" x:Top="0.75" x:Bottom="0.75"/></PageSetup><Print><ValidPrinterInfo/><PaperSizeIndex>9</PaperSizeIndex><HorizontalResolution>600</HorizontalResolution><VerticalResolution>600</VerticalResolution></Print><Selected/><TopRowVisible>18</TopRowVisible><LeftColumnVisible>0</LeftColumnVisible><Panes><Pane><Number>3</Number><ActiveRow>39</ActiveRow><ActiveCol>1</ActiveCol><RangeSelection>R40C2</RangeSelection></Pane></Panes><ProtectObjects>False</ProtectObjects><ProtectScenarios>False</ProtectScenarios></WorksheetOptions></Worksheet></Workbook>